[
  {
    "id": "1766589120166",
    "name": "Max",
    "age": "29",
    "country": "China"
  },
  {
    "id": "1766589121667",
    "name": "Dan",
    "age": "59",
    "country": "France"
  },
  {
    "id": "1766589122530",
    "name": "John",
    "age": "79",
    "country": "Sweden"
  },
  {
    "id": "1766589122994",
    "name": "Pete",
    "age": "53",
    "country": "USA"
  },
  {
    "id": "1766589124151",
    "name": "Hanna",
    "age": "42",
    "country": "France"
  },
  {
    "id": "1766589190233",
    "name": "Dan",
    "age": "20",
    "country": "China"
  },
  {
    "id": "1766593847350",
    "name": "Pete",
    "age": "82",
    "country": "France"
  },
  {
    "id": "1766595190520",
    "name": "Pete",
    "age": "68",
    "country": "China"
  },
  {
    "id": "1766595723521",
    "name": "John",
    "age": "59",
    "country": "France"
  }
]